LICENSE.txt
README.md
setup.cfg
setup.py
django_password_manager.egg-info/PKG-INFO
django_password_manager.egg-info/SOURCES.txt
django_password_manager.egg-info/dependency_links.txt
django_password_manager.egg-info/requires.txt
django_password_manager.egg-info/top_level.txt
pass_manager/__init__.py
pass_manager/admin.py
pass_manager/apps.py
pass_manager/middleware.py
pass_manager/mixin.py
pass_manager/models.py
pass_manager/settings.py
pass_manager/tests.py
pass_manager/utils.py
pass_manager/views.py
pass_manager/migrations/0001_initial.py
pass_manager/migrations/__init__.py