Metadata-Version: 2.1
Name: django-password-manager
Version: 0.1.3
Summary: Enable Password Force Reset & Maintain Password History
Home-page: https://github.com/inforian/django-password-manager
Author: Neeraj Dhiman
Author-email: ndhiman08@gmail.com
License: GPL
Download-URL: https://github.com/inforian/django-password-manager/archive/v0.1.3.tar.gz
Keywords: password,django-password,django-password-manager,django-password-manage
Platform: UNKNOWN
License-File: LICENSE.txt
